django_smart_auth_plus-0.1.0.dist-info/licenses/LICENSE
smart_auth_plus/__init__.py
smart_auth_plus/models.py
smart_auth_plus/permissions.py
smart_auth_plus/otp/__init__.py
smart_auth_plus/otp/sms_email.py
smart_auth_plus/social/__init__.py
smart_auth_plus/social/providers.py
tests/__init__.py
tests/test_auth.py
django_smart_auth_plus-0.1.0.dist-info/METADATA
django_smart_auth_plus-0.1.0.dist-info/WHEEL
django_smart_auth_plus-0.1.0.dist-info/top_level.txt
django_smart_auth_plus-0.1.0.dist-info/RECORD
