Metadata-Version: 2.4
Name: django-smart-auth-plus
Version: 0.1.0
Summary: Advanced Django Authentication package with MFA, JWT, Social Login, Role-based Permissions
Author: ProgrammerHasan
Classifier: Framework :: Django
Classifier: Programming Language :: Python :: 3
Classifier: License :: OSI Approved :: MIT License
Requires-Python: >=3.7
License-File: LICENSE
Requires-Dist: Django>=3.2
Requires-Dist: PyJWT
Requires-Dist: requests
Dynamic: author
Dynamic: classifier
Dynamic: description
Dynamic: description-content-type
Dynamic: license-file
Dynamic: requires-dist
Dynamic: requires-python
Dynamic: summary
